gs100/__init__.py
gs100/converter.py
gs100-0.0.5.dist-info/DESCRIPTION.rst
gs100-0.0.5.dist-info/METADATA
gs100-0.0.5.dist-info/RECORD
gs100-0.0.5.dist-info/WHEEL
gs100-0.0.5.dist-info/metadata.json
gs100-0.0.5.dist-info/top_level.txt
