Metadata-Version: 2.0
Name: gs100
Version: 0.0.5
Summary: Converts a notebook with student written answers to a PDF for Gradescope.
Home-page: https://github.com/DS-100/nb-to-gradescope
Author: Sam Lau
Author-email: samlau95@gmail.com
License: BSD 3-Clause
Keywords: jupyter ds100 gradescope
Platform: UNKNOWN
Classifier: Development Status :: 3 - Alpha
Classifier: Intended Audience :: Developers
Classifier: Topic :: Software Development :: Build Tools
Classifier: Programming Language :: Python :: 3
Classifier: Programming Language :: Python :: 3.3
Classifier: Programming Language :: Python :: 3.4
Classifier: Programming Language :: Python :: 3.5
Classifier: Framework :: Jupyter
Requires-Dist: toolz (>=0.8)
Requires-Dist: nbformat (>=4)
Requires-Dist: nbconvert (>=5)
Requires-Dist: beautifulsoup4 (>=4)
Requires-Dist: pdfkit (>=0.6)
Requires-Dist: PyPDF2 (>=1.26)
Provides-Extra: dev
Requires-Dist: check-manifest; extra == 'dev'
Provides-Extra: test
Requires-Dist: coverage; extra == 'test'
